LICENSE.txt
README.md
setup.py
chandralc/__init__.py
chandralc/algos.py
chandralc/analysis.py
chandralc/chandra_lightcurve.py
chandralc/config.py
chandralc/convert.py
chandralc/dotclc.py
chandralc/download.py
chandralc/galaXy.py
chandralc/ml.py
chandralc/plot.py
chandralc/states.py
chandralc.egg-info/PKG-INFO
chandralc.egg-info/SOURCES.txt
chandralc.egg-info/dependency_links.txt
chandralc.egg-info/requires.txt
chandralc.egg-info/top_level.txt
chandralc/apis/__init__.py
chandralc/apis/ads.py
chandralc/apis/viewlogs.py
chandralc/apis/vizier.py