Metadata-Version: 2.1
Name: chandralc
Version: 0.0.2a0
Summary: A Python package for CXO lightcurve analysis
Home-page: https://github.com/sammarth-k/chandralc
Author: Sammarth Kumar
Author-email: sam.kumar@yale.edu
License: MIT
Platform: UNKNOWN
